frontmatter_format/__init__.py
frontmatter_format/frontmatter_format.py
frontmatter_format/key_sort.py
frontmatter_format/py.typed
frontmatter_format/yaml_util.py
frontmatter_format-0.2.3.dist-info/METADATA
frontmatter_format-0.2.3.dist-info/WHEEL
frontmatter_format-0.2.3.dist-info/entry_points.txt
frontmatter_format-0.2.3.dist-info/licenses/LICENSE
frontmatter_format-0.2.3.dist-info/RECORD
